[{
  "_id": {
    "$oid": "658cd616fac097c3700c608c"
  },
  "id": "34bd0500-6e8e-4db2-88b1-c4f005e1686c",
  "type": "city",
  "name": "Auranthia",
  "img": "https://bayaz.s3.eu-north-1.amazonaws.com/images/places/city/medium_temple_tavern_4512345.png",
  "population": 10000,
  "accommodation": [
    "La Pluma Veloz",
    "El Cuervo Sacrificado",
    "El Jabalí Pálido",
    "El Martillo Ladrador",
    "La Lanza de Oropel",
    "El Oso Panorámico",
    "El Corzo Naranja"
  ],
  "government": {
    "type": "OLIGARCHY",
    "situation": "Liderazgo disputado, lucha abierta",
    "_id": {
      "$oid": "658cd66cfac097c3700c609c"
    }
  },
  "security": 80,
  "securityType": "guards",
  "commerces": [
    "TRADING",
    "WOODWORK",
    "STEELWORK"
  ],
  "religion": {
    "temples": [
      "Dshim (Energía)",
      "Abnu (Materia)"
    ],
    "shrines": [
      "Burumu (Espacio)",
      "Kabattu (Espiritu)"
    ],
    "_id": {
      "$oid": "658cd66cfac097c3700c609b"
    }
  },
  "magicShops": 1,
  "raceRelationships": "Armonía",
  "knownFor": "Gremios poderosos",
  "calamity": "Escándalo que amenaza a familias poderosas",
  "notes": "- Lugar de nacimiento de Neylen",
  "__v": 0
},{
  "_id": {
    "$oid": "65a1f1df3c41d7f3f0f5a8bd"
  },
  "id": "9ccf0935-aba6-4342-afd5-bccdb1d860fb",
  "type": "city",
  "name": "Gran Bwini",
  "img": "https://bayaz.s3.eu-north-1.amazonaws.com/images/places/city/medium_castle_coast_23453465.png",
  "population": 6000,
  "accommodation": [
    "El Druida de Acero",
    "El Gólem Aullador",
    "El Poeta Marrón",
    "La Mula Ceiluda",
    "El Ópalo Mentiroso"
  ],
  "government": {
    "type": "TEOCRACY",
    "situation": "De voluntad férrea pero respetado",
    "_id": {
      "$oid": "65a1f4373c41d7f3f0f5a8cd"
    }
  },
  "security": 40,
  "securityType": "guards",
  "commerces": [
    "MAGIC",
    "TRADING"
  ],
  "religion": {
    "temples": [
      "Abaru (Energía)"
    ],
    "shrines": [
      "Abnu (Materia)"
    ],
    "_id": {
      "$oid": "65a1f4373c41d7f3f0f5a8cc"
    }
  },
  "magicShops": 2,
  "raceRelationships": "Armonía",
  "placeCharacteristics": "Templo grandioso",
  "knownFor": "Devoción",
  "calamity": "Saqueos por parte de monstruos",
  "__v": 0,
  "notes": "- Lugar donde creció Petra\n- Ciudad de origen de:\n   - Nekane (Clériga de Abaru)\n   - Rayland (Bardo)\n- Templo a Abaru\n   - Se dedica a combatir sectas e incursiones en la zona"
}]